veespeech/__init__.py
veespeech/exceptions.py
veespeech/file_utils.py
veespeech/models/faster_whisper.py
veespeech/models/model_base.py
veespeech/models/whisper.py
veespeech/py.typed
veeper_speech-0.3.3.dist-info/LICENSE
veeper_speech-0.3.3.dist-info/METADATA
veeper_speech-0.3.3.dist-info/WHEEL
veeper_speech-0.3.3.dist-info/RECORD
