Metadata-Version: 2.1
Name: veeper-speech
Version: 0.3.3
Summary: 
Author: Igor Avdonin
Author-email: avdonin.pb@yandex.ru
Requires-Python: >=3.10,<3.14
Classifier: Programming Language :: Python :: 3
Classifier: Programming Language :: Python :: 3.10
Classifier: Programming Language :: Python :: 3.11
Classifier: Programming Language :: Python :: 3.12
Requires-Dist: faster-whisper (>=1.0.0,<2.0.0)
Requires-Dist: openai-whisper (>=20250625,<20250626)
Requires-Dist: soundfile (>=0.13.0,<0.14.0)
Requires-Dist: torch (>2.0.0,<3.0.0)
Requires-Dist: torchaudio (>2.0.0,<3.0.0)
Requires-Dist: transformers (>=4.0.0,<5.0.0)
